{
    "monthly-working-report": {
        "type": "band",
        "values": [
            {
                "Name": "김ㅇㅇ",
                "Position": "과장",
                "D1": "",
                "D2": "",
                "D3": "연",
                "D4": "연",
                "D5": "",
                "D6": "",
                "D7": "",
                "D8": "",
                "D9": "",
                "D10": "",
                "D11": "",
                "D12": "",
                "D13": "",
                "D14": "",
                "D15": "",
                "D16": "",
                "D17": "",
                "D18": "",
                "D19": "",
                "D20": "",
                "D21": "",
                "D22": "",
                "D23": "",
                "D24": "",
                "D25": "",
                "D26": "",
                "D27": "휴",
                "D28": "",
                "D29": "",
                "D30": "",
                "D31": "",
                "Normal": 21,
                "Late": 0,
                "Leave": 0,
                "Holiday": 2,
                "Overtime": 0,
                "WorkingDay": 23
            },
            {
                "Name": "강ㅇㅇ",
                "Position": "대리",
                "D1": "",
                "D2": "연",
                "D3": "",
                "D4": "",
                "D5": "",
                "D6": "",
                "D7": "",
                "D8": "",
                "D9": "",
                "D10": "",
                "D11": "",
                "D12": "",
                "D13": "",
                "D14": "",
                "D15": "",
                "D16": "",
                "D17": "",
                "D18": "",
                "D19": "",
                "D20": "",
                "D21": "",
                "D22": "",
                "D23": "",
                "D24": "",
                "D25": "",
                "D26": "",
                "D27": "",
                "D28": "",
                "D29": "",
                "D30": "",
                "D31": "",
                "Normal": 22,
                "Late": 0,
                "Leave": 0,
                "Holiday": 1,
                "Overtime": 2,
                "WorkingDay": 23
            },
            {
                "Name": "신ㅇㅇ",
                "Position": "대리",
                "D1": "",
                "D2": "",
                "D3": "",
                "D4": "",
                "D5": "",
                "D6": "",
                "D7": "",
                "D8": "",
                "D9": "",
                "D10": "",
                "D11": "",
                "D12": "",
                "D13": "",
                "D14": "",
                "D15": "지",
                "D16": "",
                "D17": "",
                "D18": "",
                "D19": "",
                "D20": "",
                "D21": "",
                "D22": "",
                "D23": "연",
                "D24": "",
                "D25": "",
                "D26": "",
                "D27": "",
                "D28": "",
                "D29": "",
                "D30": "",
                "D31": "조",
                "Normal": 20,
                "Late": 1,
                "Leave": 1,
                "Holiday": 1,
                "Overtime": 0,
                "WorkingDay": 23
            },
            {
                "Name": "허ㅇㅇ",
                "Position": "사원",
                "D1": "",
                "D2": "",
                "D3": "",
                "D4": "",
                "D5": "",
                "D6": "",
                "D7": "",
                "D8": "",
                "D9": "",
                "D10": "연",
                "D11": "",
                "D12": "",
                "D13": "",
                "D14": "",
                "D15": "",
                "D16": "",
                "D17": "",
                "D18": "",
                "D19": "",
                "D20": "",
                "D21": "",
                "D22": "",
                "D23": "",
                "D24": "",
                "D25": "",
                "D26": "",
                "D27": "",
                "D28": "",
                "D29": "",
                "D30": "",
                "D31": "",
                "Normal": 22,
                "Late": 0,
                "Leave": 0,
                "Holiday": 1,
                "Overtime": 0,
                "WorkingDay": 23
            },
            {
                "Name": "차ㅇㅇ",
                "Position": "사원",
                "D1": "",
                "D2": "",
                "D3": "",
                "D4": "",
                "D5": "",
                "D6": "",
                "D7": "",
                "D8": "",
                "D9": "",
                "D10": "",
                "D11": "",
                "D12": "",
                "D13": "",
                "D14": "",
                "D15": "",
                "D16": "",
                "D17": "",
                "D18": "",
                "D19": "",
                "D20": "",
                "D21": "",
                "D22": "",
                "D23": "",
                "D24": "",
                "D25": "",
                "D26": "",
                "D27": "",
                "D28": "",
                "D29": "",
                "D30": "",
                "D31": "",
                "Normal": 23,
                "Late": 0,
                "Leave": 0,
                "Holiday": 0,
                "Overtime": 0,
                "WorkingDay": 23
            },
            {
                "Name": "이ㅇㅇ",
                "Position": "사원",
                "D1": "",
                "D2": "",
                "D3": "",
                "D4": "",
                "D5": "",
                "D6": "",
                "D7": "",
                "D8": "",
                "D9": "",
                "D10": "",
                "D11": "",
                "D12": "",
                "D13": "",
                "D14": "",
                "D15": "",
                "D16": "",
                "D17": "",
                "D18": "",
                "D19": "",
                "D20": "",
                "D21": "",
                "D22": "",
                "D23": "",
                "D24": "",
                "D25": "",
                "D26": "",
                "D27": "",
                "D28": "",
                "D29": "",
                "D30": "",
                "D31": "",
                "Normal": 23,
                "Late": 0,
                "Leave": 0,
                "Holiday": 0,
                "Overtime": 0,
                "WorkingDay": 23
            },
            {
                "Name": "정ㅇㅇ",
                "Position": "사원",
                "D1": "",
                "D2": "",
                "D3": "",
                "D4": "연",
                "D5": "",
                "D6": "",
                "D7": "",
                "D8": "",
                "D9": "",
                "D10": "",
                "D11": "",
                "D12": "",
                "D13": "",
                "D14": "",
                "D15": "",
                "D16": "",
                "D17": "",
                "D18": "",
                "D19": "",
                "D20": "",
                "D21": "",
                "D22": "",
                "D23": "",
                "D24": "",
                "D25": "",
                "D26": "",
                "D27": "",
                "D28": "",
                "D29": "",
                "D30": "",
                "D31": "",
                "Normal": 22,
                "Late": 0,
                "Leave": 0,
                "Holiday": 1,
                "Overtime": 0,
                "WorkingDay": 23
            },
            {
                "Name": "김ㅇㅇ",
                "Position": "사원",
                "D1": "",
                "D2": "",
                "D3": "",
                "D4": "",
                "D5": "",
                "D6": "",
                "D7": "",
                "D8": "",
                "D9": "",
                "D10": "",
                "D11": "",
                "D12": "",
                "D13": "",
                "D14": "",
                "D15": "",
                "D16": "",
                "D17": "",
                "D18": "",
                "D19": "조",
                "D20": "",
                "D21": "",
                "D22": "",
                "D23": "",
                "D24": "",
                "D25": "",
                "D26": "",
                "D27": "",
                "D28": "",
                "D29": "",
                "D30": "",
                "D31": "",
                "Normal": 22,
                "Late": 0,
                "Leave": 1,
                "Holiday": 0,
                "Overtime": 0,
                "WorkingDay": 23
            },
            {
                "Name": "오ㅇㅇ",
                "Position": "사원",
                "D1": "",
                "D2": "",
                "D3": "지",
                "D4": "",
                "D5": "",
                "D6": "",
                "D7": "",
                "D8": "",
                "D9": "",
                "D10": "",
                "D11": "",
                "D12": "조",
                "D13": "",
                "D14": "",
                "D15": "",
                "D16": "",
                "D17": "",
                "D18": "조",
                "D19": "",
                "D20": "",
                "D21": "",
                "D22": "",
                "D23": "",
                "D24": "",
                "D25": "",
                "D26": "",
                "D27": "",
                "D28": "",
                "D29": "",
                "D30": "",
                "D31": "",
                "Normal": 20,
                "Late": 1,
                "Leave": 2,
                "Holiday": 0,
                "Overtime": 1,
                "WorkingDay": 23
            },
            {
                "Name": "윤ㅇㅇ",
                "Position": "사원",
                "D1": "지",
                "D2": "지",
                "D3": "지",
                "D4": "",
                "D5": "",
                "D6": "",
                "D7": "",
                "D8": "",
                "D9": "",
                "D10": "",
                "D11": "",
                "D12": "",
                "D13": "",
                "D14": "",
                "D15": "연",
                "D16": "",
                "D17": "",
                "D18": "",
                "D19": "",
                "D20": "",
                "D21": "",
                "D22": "",
                "D23": "",
                "D24": "",
                "D25": "연",
                "D26": "",
                "D27": "",
                "D28": "",
                "D29": "",
                "D30": "",
                "D31": "",
                "Normal": 18,
                "Late": 3,
                "Leave": 0,
                "Holiday": 2,
                "Overtime": 0,
                "WorkingDay": 23
            },
            {
                "Name": "지ㅇㅇ",
                "Position": "사원",
                "D1": "",
                "D2": "",
                "D3": "",
                "D4": "",
                "D5": "",
                "D6": "",
                "D7": "",
                "D8": "",
                "D9": "",
                "D10": "",
                "D11": "",
                "D12": "",
                "D13": "",
                "D14": "",
                "D15": "",
                "D16": "",
                "D17": "",
                "D18": "",
                "D19": "",
                "D20": "",
                "D21": "",
                "D22": "",
                "D23": "",
                "D24": "",
                "D25": "",
                "D26": "",
                "D27": "",
                "D28": "",
                "D29": "",
                "D30": "",
                "D31": "",
                "Normal": 23,
                "Late": 0,
                "Leave": 0,
                "Holiday": 0,
                "Overtime": 0,
                "WorkingDay": 23
            }
        ]
    }
}
